{
    "article_id": "10609370_remove-chocolate-stains-from-clothes",
    "url": "https://www.wikihow.com/Remove-Chocolate-Stains-from-Clothes",
    "steps": [
        [
            {
                "token_id": "0-0-0",
                "token": "Dab",
                "ne_tag": "Ae-B"
            },
            {
                "token_id": "0-0-1",
                "token": "vinegar",
                "ne_tag": "T-B"
            },
            {
                "token_id": "0-0-2",
                "token": "onto",
                "ne_tag": "O"
            },
            {
                "token_id": "0-0-3",
                "token": "the",
                "ne_tag": "O"
            },
            {
                "token_id": "0-0-4",
                "token": "stain",
                "ne_tag": "I-B"
            },
            {
                "token_id": "0-0-5",
                "token": "and",
                "ne_tag": "I-B"
            },
            {
                "token_id": "0-0-6",
                "token": "let",
                "ne_tag": "Ae-B"
            },
            {
                "token_id": "0-0-7",
                "token": "it",
                "ne_tag": "I-B"
            },
            {
                "token_id": "0-0-8",
                "token": "sit",
                "ne_tag": "Ai-B"
            },
            {
                "token_id": "0-0-9",
                "token": "for",
                "ne_tag": "Ai-B"
            },
            {
                "token_id": "0-0-10",
                "token": "5",
                "ne_tag": "D-B"
            },
            {
                "token_id": "0-0-11",
                "token": "minutes",
                "ne_tag": "D-I"
            },
            {
                "token_id": "0-0-12",
                "token": ".",
                "ne_tag": "O"
            }
        ],
        [
            {
                "token_id": "1-0-0",
                "token": "Rinse",
                "ne_tag": "Ae-B"
            },
            {
                "token_id": "1-0-1",
                "token": "the",
                "ne_tag": "Ae-B"
            },
            {
                "token_id": "1-0-2",
                "token": "stain",
                "ne_tag": "I-B"
            },
            {
                "token_id": "1-0-3",
                "token": "with",
                "ne_tag": "I-B"
            },
            {
                "token_id": "1-0-4",
                "token": "water",
                "ne_tag": "T-B"
            },
            {
                "token_id": "1-0-5",
                "token": "to",
                "ne_tag": "O"
            },
            {
                "token_id": "1-0-6",
                "token": "remove",
                "ne_tag": "Ae-B"
            },
            {
                "token_id": "1-0-7",
                "token": "the",
                "ne_tag": "Ae-B"
            },
            {
                "token_id": "1-0-8",
                "token": "vinegar",
                "ne_tag": "T-B"
            },
            {
                "token_id": "1-0-9",
                "token": ".",
                "ne_tag": "O"
            }
        ],
        [
            {
                "token_id": "2-0-0",
                "token": "Apply",
                "ne_tag": "Ae-B"
            },
            {
                "token_id": "2-0-1",
                "token": "dish",
                "ne_tag": "T-B"
            },
            {
                "token_id": "2-0-2",
                "token": "detergent",
                "ne_tag": "T-I"
            },
            {
                "token_id": "2-0-3",
                "token": "and",
                "ne_tag": "O"
            },
            {
                "token_id": "2-0-4",
                "token": "water",
                "ne_tag": "T-B"
            },
            {
                "token_id": "2-0-5",
                "token": "to",
                "ne_tag": "O"
            },
            {
                "token_id": "2-0-6",
                "token": "the",
                "ne_tag": "O"
            },
            {
                "token_id": "2-0-7",
                "token": "reverse",
                "ne_tag": "I-B"
            },
            {
                "token_id": "2-0-8",
                "token": "side",
                "ne_tag": "I-I"
            },
            {
                "token_id": "2-0-9",
                "token": "of",
                "ne_tag": "I-I"
            },
            {
                "token_id": "2-0-10",
                "token": "the",
                "ne_tag": "I-I"
            },
            {
                "token_id": "2-0-11",
                "token": "stained",
                "ne_tag": "Si-B"
            },
            {
                "token_id": "2-0-12",
                "token": "fabric",
                "ne_tag": "I-B"
            },
            {
                "token_id": "2-0-13",
                "token": ".",
                "ne_tag": "I-B"
            }
        ],
        [
            {
                "token_id": "3-0-0",
                "token": "Wash",
                "ne_tag": "Ae-B"
            },
            {
                "token_id": "3-0-1",
                "token": "the",
                "ne_tag": "Ae-B"
            },
            {
                "token_id": "3-0-2",
                "token": "clothing",
                "ne_tag": "I-B"
            },
            {
                "token_id": "3-0-3",
                "token": "as",
                "ne_tag": "I-B"
            },
            {
                "token_id": "3-0-4",
                "token": "usual",
                "ne_tag": "I-B"
            },
            {
                "token_id": "3-0-5",
                "token": "in",
                "ne_tag": "I-B"
            },
            {
                "token_id": "3-0-6",
                "token": "the",
                "ne_tag": "I-B"
            },
            {
                "token_id": "3-0-7",
                "token": "washing",
                "ne_tag": "T-B"
            },
            {
                "token_id": "3-0-8",
                "token": "machine",
                "ne_tag": "T-I"
            },
            {
                "token_id": "3-0-9",
                "token": "or",
                "ne_tag": "O"
            },
            {
                "token_id": "3-0-10",
                "token": "by",
                "ne_tag": "O"
            },
            {
                "token_id": "3-0-11",
                "token": "hand",
                "ne_tag": "T-B"
            },
            {
                "token_id": "3-0-12",
                "token": ".",
                "ne_tag": "O"
            }
        ],
        [
            {
                "token_id": "4-0-0",
                "token": "Check",
                "ne_tag": "Ae-B"
            },
            {
                "token_id": "4-0-1",
                "token": "that",
                "ne_tag": "Ae-B"
            },
            {
                "token_id": "4-0-2",
                "token": "the",
                "ne_tag": "Ae-B"
            },
            {
                "token_id": "4-0-3",
                "token": "stain",
                "ne_tag": "I-B"
            },
            {
                "token_id": "4-0-4",
                "token": "is",
                "ne_tag": "I-B"
            },
            {
                "token_id": "4-0-5",
                "token": "completely",
                "ne_tag": "I-B"
            },
            {
                "token_id": "4-0-6",
                "token": "gone",
                "ne_tag": "Ai-B"
            },
            {
                "token_id": "4-0-7",
                "token": "before",
                "ne_tag": "Ai-B"
            },
            {
                "token_id": "4-0-8",
                "token": "drying",
                "ne_tag": "Ae-B"
            },
            {
                "token_id": "4-0-9",
                "token": "the",
                "ne_tag": "Ae-B"
            },
            {
                "token_id": "4-0-10",
                "token": "clothing",
                "ne_tag": "I-B"
            },
            {
                "token_id": "4-0-11",
                "token": ".",
                "ne_tag": "I-B"
            }
        ]
    ],
    "flows": [
        [
            "0-0-0",
            "0-0-7",
            "I-eq"
        ],
        [
            "0-0-1",
            "0-0-0",
            "Targ"
        ],
        [
            "0-0-10",
            "0-0-6",
            "other-mod"
        ],
        [
            "0-0-4",
            "0-0-0",
            "Dest"
        ],
        [
            "0-0-6",
            "0-0-8",
            "Agent"
        ],
        [
            "0-0-7",
            "0-0-6",
            "Targ"
        ],
        [
            "0-0-8",
            "1-0-2",
            "I-eq"
        ],
        [
            "1-0-0",
            "1-0-8",
            "T-part-of"
        ],
        [
            "1-0-2",
            "1-0-0",
            "Targ"
        ],
        [
            "1-0-4",
            "1-0-0",
            "T-comp"
        ],
        [
            "1-0-6",
            "2-0-12",
            "I-eq"
        ],
        [
            "1-0-8",
            "1-0-6",
            "Targ"
        ],
        [
            "2-0-0",
            "3-0-2",
            "I-eq"
        ],
        [
            "2-0-1",
            "2-0-0",
            "Targ"
        ],
        [
            "2-0-11",
            "2-0-12",
            "other-mod"
        ],
        [
            "2-0-12",
            "2-0-7",
            "I-part-of"
        ],
        [
            "2-0-4",
            "2-0-0",
            "Targ"
        ],
        [
            "2-0-7",
            "2-0-0",
            "Dest"
        ],
        [
            "3-0-0",
            "4-0-10",
            "I-eq"
        ],
        [
            "3-0-0",
            "4-0-3",
            "I-part-of"
        ],
        [
            "3-0-11",
            "3-0-0",
            "T-comp"
        ],
        [
            "3-0-2",
            "3-0-0",
            "Targ"
        ],
        [
            "3-0-7",
            "3-0-0",
            "T-comp"
        ],
        [
            "4-0-10",
            "4-0-8",
            "Targ"
        ],
        [
            "4-0-3",
            "4-0-6",
            "Agent"
        ],
        [
            "4-0-6",
            "4-0-0",
            "Targ"
        ],
        [
            "4-0-8",
            "4-0-0",
            "V-tm"
        ]
    ]
}